qualang_tools/__init__.py
qualang_tools/addons/InteractivePlotLib.py
qualang_tools/addons/InteractivePlotLib_demonstration.png
qualang_tools/addons/README.md
qualang_tools/addons/__init__.py
qualang_tools/addons/calibration/README.md
qualang_tools/addons/calibration/calibrations.py
qualang_tools/addons/calibration/rabi.PNG
qualang_tools/addons/calibration/ramsey.PNG
qualang_tools/addons/calibration/raw_traces.PNG
qualang_tools/addons/calibration/time_of_flight.PNG
qualang_tools/addons/variables.py
qualang_tools/analysis/IQ.png
qualang_tools/analysis/README.md
qualang_tools/analysis/__init__.py
qualang_tools/analysis/discriminator.py
qualang_tools/bakery/README.md
qualang_tools/bakery/__init__.py
qualang_tools/bakery/bakery.py
qualang_tools/bakery/randomized_benchmark.py
qualang_tools/bakery/randomized_benchmark_c1.py
qualang_tools/bakery/xeb.py
qualang_tools/callable_from_qua/__init__.py
qualang_tools/callable_from_qua/_callable_from_qua.py
qualang_tools/callable_from_qua/_qua_patches.py
qualang_tools/callable_from_qua/readme.md
qualang_tools/characterization/README.md
qualang_tools/characterization/__init__.py
qualang_tools/characterization/two_qubit_rb/.img/debugging.png
qualang_tools/characterization/two_qubit_rb/.img/runtime.png
qualang_tools/characterization/two_qubit_rb/.img/setup.png
qualang_tools/characterization/two_qubit_rb/README.md
qualang_tools/characterization/two_qubit_rb/__init__.py
qualang_tools/characterization/two_qubit_rb/two_qubit_rb/RBBaker.py
qualang_tools/characterization/two_qubit_rb/two_qubit_rb/RBResult.py
qualang_tools/characterization/two_qubit_rb/two_qubit_rb/TwoQubitRB.py
qualang_tools/characterization/two_qubit_rb/two_qubit_rb/TwoQubitRBDebugger.py
qualang_tools/characterization/two_qubit_rb/two_qubit_rb/__init__.py
qualang_tools/characterization/two_qubit_rb/two_qubit_rb/_cirq.py
qualang_tools/characterization/two_qubit_rb/two_qubit_rb/gates.py
qualang_tools/characterization/two_qubit_rb/two_qubit_rb/simple_tableau.py
qualang_tools-0.20.1.dist-info/METADATA
qualang_tools-0.20.1.dist-info/WHEEL
qualang_tools-0.20.1.dist-info/licenses/LICENSE
qualang_tools-0.20.1.dist-info/RECORD
