Metadata-Version: 2.4
Name: qualang-tools
Version: 0.20.1
Summary: The qualang_tools package includes various tools related to QUA programs in Python
License: BSD-3-Clause
License-File: LICENSE
Author: Quantum Machines
Author-email: info@quantum-machines.co
Requires-Python: >=3.9,<3.13
Classifier: License :: OSI Approved :: BSD License
Classifier: Programming Language :: Python :: 3
Classifier: Programming Language :: Python :: 3.9
Classifier: Programming Language :: Python :: 3.10
Classifier: Programming Language :: Python :: 3.11
Classifier: Programming Language :: Python :: 3.12
Provides-Extra: configbuilder
Provides-Extra: datahandler
Provides-Extra: interplot
Provides-Extra: two-qubit-rb
Requires-Dist: cirq (==1.2.0) ; (python_version >= "3.10") and (extra == "two-qubit-rb")
Requires-Dist: dash (>=2.0.0,<3.0.0) ; extra == "configbuilder"
Requires-Dist: dash-bootstrap-components (>=1.6.0,<2.0.0) ; extra == "configbuilder"
Requires-Dist: dash-core-components (>=2.0.0,<3.0.0) ; extra == "configbuilder"
Requires-Dist: dash-cytoscape (>=0.3.0,<0.4.0) ; extra == "configbuilder"
Requires-Dist: dash-dangerously-set-inner-html (>=0.0.2,<0.0.3) ; extra == "configbuilder"
Requires-Dist: dash-html-components (>=2.0.0,<3.0.0) ; extra == "configbuilder"
Requires-Dist: dash-table (>=5.0.0,<6.0.0) ; extra == "configbuilder"
Requires-Dist: dill (>=0.3.4,<0.4.0) ; extra == "interplot"
Requires-Dist: docutils (>=0.14.0,<=0.21) ; extra == "configbuilder"
Requires-Dist: grpclib (==0.4.5)
Requires-Dist: ipython (>=8.10.0,<9.0.0) ; extra == "interplot"
Requires-Dist: matplotlib (>=3.8.0,<4.0.0)
Requires-Dist: netCDF4 (>=1.7.2,<2.0.0) ; extra == "datahandler"
Requires-Dist: numpy (>=1.26.0,<2)
Requires-Dist: pandas (>=1.2.4) ; extra == "configbuilder"
Requires-Dist: pypiwin32 (>=223,<224) ; (sys_platform == "win32") and (extra == "interplot")
Requires-Dist: qm-qua (>=1.2.2)
Requires-Dist: scikit-learn (>=1.5.0)
Requires-Dist: scipy (>=1.11.0)
Requires-Dist: tqdm (>=4.67.1,<5.0.0) ; extra == "two-qubit-rb"
Requires-Dist: waitress (>=3.0.1,<4.0.0) ; extra == "configbuilder"
Requires-Dist: xarray (>=2023.0.0,<2024.0.0) ; extra == "datahandler" or extra == "two-qubit-rb"
Project-URL: Homepage, https://github.com/qua-platform/py-qua-tools
